ytcook/__init__.py
ytcook-0.1.0.dist-info/licenses/LICENSE
ytcook-0.1.0.dist-info/METADATA
ytcook-0.1.0.dist-info/WHEEL
ytcook-0.1.0.dist-info/top_level.txt
ytcook-0.1.0.dist-info/RECORD
