Metadata-Version: 2.4
Name: ytcook
Version: 0.1.0
Summary: Auto cookie extractor for YouTube using browser-cookie3
Home-page: https://github.com/ToN-Service/ytcook
Author: Ahmed
Author-email: support@ton-service.info
Classifier: Programming Language :: Python :: 3
Classifier: License :: OSI Approved :: MIT License
Classifier: Operating System :: OS Independent
Requires-Python: >=3.7
License-File: LICENSE
Requires-Dist: browser-cookie3
Dynamic: author
Dynamic: author-email
Dynamic: classifier
Dynamic: description
Dynamic: description-content-type
Dynamic: home-page
Dynamic: license-file
Dynamic: requires-dist
Dynamic: requires-python
Dynamic: summary
